hrvanalysis/__init__.py
hrvanalysis/extract_features.py
hrvanalysis/plot.py
hrvanalysis/preprocessing.py
hrv_analysis-1.0.4.dist-info/LICENSE
hrv_analysis-1.0.4.dist-info/METADATA
hrv_analysis-1.0.4.dist-info/WHEEL
hrv_analysis-1.0.4.dist-info/top_level.txt
hrv_analysis-1.0.4.dist-info/RECORD
