Metadata-Version: 2.1
Name: hrv-analysis
Version: 1.0.4
Summary: a package to calculate features from Rr Interval for HRV analyses
Home-page: https://github.com/Aura-healthcare/hrvanalysis
Author: Robin Champseix
Author-email: robin.champseix@gmail.com
License: GPLv3
Platform: UNKNOWN
Classifier: Programming Language :: Python :: 3
Classifier: Operating System :: OS Independent
Requires-Python: >=3.5
